prompt_sentinel-0.1.4.dist-info/licenses/LICENSE
sentinel/__init__.py
sentinel/prompt_sentinel.py
sentinel/secret_context.py
sentinel/sentinel_detectors.py
sentinel/test.py
sentinel/test_presidio.py
sentinel/utils.py
sentinel/wrappers.py
prompt_sentinel-0.1.4.dist-info/METADATA
prompt_sentinel-0.1.4.dist-info/WHEEL
prompt_sentinel-0.1.4.dist-info/entry_points.txt
prompt_sentinel-0.1.4.dist-info/top_level.txt
prompt_sentinel-0.1.4.dist-info/RECORD
