Metadata-Version: 2.4
Name: prompt-sentinel
Version: 0.1.4
Summary: A package for sentinel detectors and utilities
Author-email: George Kour <kourgeorge@gmail.com>
License-Expression: MIT
Keywords: LLM,security,privacy,sanitization,masking,prompt sanitization,secret detection
Classifier: Development Status :: 3 - Alpha
Classifier: Intended Audience :: Developers
Classifier: Topic :: Software Development :: Libraries
Classifier: Programming Language :: Python :: 3
Classifier: Programming Language :: Python :: 3.8
Classifier: Operating System :: OS Independent
Requires-Python: >=3.8
License-File: LICENSE
Provides-Extra: langchain
Requires-Dist: langchain>=0.1.0; extra == "langchain"
Provides-Extra: examples
Requires-Dist: matplotlib; extra == "examples"
Requires-Dist: jupyter; extra == "examples"
Requires-Dist: pandas; extra == "examples"
Requires-Dist: langchain>=0.1.0; extra == "examples"
Provides-Extra: test
Requires-Dist: pytest; extra == "test"
Requires-Dist: coverage; extra == "test"
Provides-Extra: dev
Requires-Dist: langchain>=0.1.0; extra == "dev"
Requires-Dist: pytest; extra == "dev"
Requires-Dist: black; extra == "dev"
Requires-Dist: flake8; extra == "dev"
Requires-Dist: mypy; extra == "dev"
Requires-Dist: jupyter; extra == "dev"
Requires-Dist: matplotlib; extra == "dev"
Requires-Dist: pandas; extra == "dev"
Dynamic: license-file
